_ibims_version.py
ibims/__init__.py
ibims/py.typed
ibims/bo4e/__init__.py
ibims/bo4e/__version__.py
ibims/bo4e/zusatz_attribut.py
ibims/bo4e/bo/__init__.py
ibims/bo4e/bo/angebot.py
ibims/bo4e/bo/ausschreibung.py
ibims/bo4e/bo/bilanzierung.py
ibims/bo4e/bo/buendelvertrag.py
ibims/bo4e/bo/dokument.py
ibims/bo4e/bo/energiemenge.py
ibims/bo4e/bo/file.py
ibims/bo4e/bo/fremdkosten.py
ibims/bo4e/bo/geraet.py
ibims/bo4e/bo/geschaeftspartner.py
ibims/bo4e/bo/hinweis.py
ibims/bo4e/bo/kampagne.py
ibims/bo4e/bo/kosten.py
ibims/bo4e/bo/lastgang.py
ibims/bo4e/bo/lokationszuordnung.py
ibims/bo4e/bo/marktlokation.py
ibims/bo4e/bo/marktteilnehmer.py
ibims/bo4e/bo/messlokation.py
ibims/bo4e/bo/netzlokation.py
ibims/bo4e/bo/person.py
ibims/bo4e/bo/preisblatt.py
ibims/bo4e/bo/preisblatt_dienstleistung.py
ibims/bo4e/bo/preisblatt_hardware.py
ibims/bo4e/bo/preisblatt_konzessionsabgabe.py
ibims/bo4e/bo/preisblatt_messung.py
ibims/bo4e/bo/preisblatt_netznutzung.py
ibims/bo4e/bo/rechnung.py
ibims/bo4e/bo/region.py
ibims/bo4e/bo/regionaltarif.py
ibims/bo4e/bo/standorteigenschaften.py
ibims/bo4e/bo/steuerbare_ressource.py
ibims/bo4e/bo/tarif.py
ibims/bo4e/bo/tarifinfo.py
ibims/bo4e/bo/tarifkosten.py
ibims/bo4e/bo/tarifpreisblatt.py
ibims/bo4e/bo/technische_ressource.py
ibims/bo4e/bo/transaktionsdaten_invoices.py
ibims/bo4e/bo/transaktionsdaten_quantities.py
ibims/bo4e/bo/vertrag.py
ibims/bo4e/bo/zaehler.py
ibims/bo4e/bo/zaehler_gas.py
ibims/bo4e/bo/zeitreihe.py
ibims/bo4e/com/__init__.py
ibims/bo4e/com/adresse.py
ibims/bo4e/com/angebotsposition.py
ibims/bo4e/com/angebotsteil.py
ibims/bo4e/com/angebotsvariante.py
ibims/bo4e/com/auf_abschlag.py
ibims/bo4e/com/auf_abschlag_pro_ort.py
ibims/bo4e/com/auf_abschlag_regional.py
ibims/bo4e/com/auf_abschlagstaffel_pro_ort.py
ibims/bo4e/com/ausschreibungsdetail.py
ibims/bo4e/com/ausschreibungslos.py
ibims/bo4e/com/bankverbindung.py
ibims/bo4e/com/betrag.py
ibims/bo4e/com/concession_fee.py
ibims/bo4e/com/dienstleistung.py
ibims-0.3.6.dist-info/METADATA
ibims-0.3.6.dist-info/WHEEL
ibims-0.3.6.dist-info/licenses/LICENSE
ibims-0.3.6.dist-info/RECORD
