Metadata-Version: 2.3
Name: ibims
Version: 0.3.6
Summary: A Pydantic based BO4E data model that is inteded to be used in data migrations from one system to another
Project-URL: Changelog, https://github.com/Hochfrequenz/intermediate-bo4e-migration-models/releases
Project-URL: Homepage, https://github.com/Hochfrequenz/intermediate-bo4e-migration-models
Author-email: Hochfrequenz Unternehmensberatung GmbH <info@hochfrequenz.de>
License: MIT
License-File: LICENSE
Keywords: bo4e,migration,pydantic
Classifier: Development Status :: 4 - Beta
Classifier: Environment :: Console
Classifier: Intended Audience :: Developers
Classifier: License :: OSI Approved :: MIT License
Classifier: Operating System :: OS Independent
Classifier: Programming Language :: Python
Classifier: Programming Language :: Python :: 3 :: Only
Classifier: Programming Language :: Python :: 3.11
Classifier: Programming Language :: Python :: 3.12
Requires-Python: >=3.11
Requires-Dist: bomf>=0.6.8
